asgirefs/__init__.py
asgirefs/manage.py
asgirefs/api/__init__.py
asgirefs/api/admin.py
asgirefs/api/apps.py
asgirefs/api/authentication.py
asgirefs/api/handler.py
asgirefs/api/models.py
asgirefs/api/serializers.py
asgirefs/api/tests.py
asgirefs/api/urls.py
asgirefs/api/views.py
asgirefs/api/migrations/0001_initial.py
asgirefs/api/migrations/__init__.py
asgirefs/core/__init__.py
asgirefs/core/asgi.py
asgirefs/core/settings.py
asgirefs/core/urls.py
asgirefs/core/wsgi.py
asgirefs-1.0.0.dist-info/METADATA
asgirefs-1.0.0.dist-info/WHEEL
asgirefs-1.0.0.dist-info/top_level.txt
asgirefs-1.0.0.dist-info/RECORD
