Metadata-Version: 2.1
Name: asgirefs
Version: 1.0.0
Summary: This is the simplest module for quick work with files.
Author: asgiii
Author-email: gamerpetushkov@gmail.com
Keywords: ASGI library
Classifier: Programming Language :: Python :: 3.10
Classifier: License :: OSI Approved :: MIT License
Classifier: Operating System :: OS Independent
Requires-Python: >=3.5
